MANIFEST.in
README.md
setup.py
kextractor/confdata.c
kextractor/expr.c
kextractor/expr.h
kextractor/images.h
kextractor/kextractor.c
kextractor/kextractor_extension.c
kextractor/lexer.lex.c
kextractor/list.h
kextractor/lkc.h
kextractor/lkc_proto.h
kextractor/menu.c
kextractor/nconf.h
kextractor/parser.tab.c
kextractor/parser.tab.h
kextractor/preprocess.c
kextractor/qconf.h
kextractor/symbol.c
kextractor/util.c
kextractor/lxdialog/dialog.h
kmaxtools/__init__.py
kmaxtools/about.py
kmaxtools/alg.py
kmaxtools/analysis.py
kmaxtools/datastructures.py
kmaxtools/expression_converter.py
kmaxtools/kclause
kmaxtools/kextract
kmaxtools/klocalizer
kmaxtools/kmax
kmaxtools/kmaxall
kmaxtools/linux_case_study.py
kmaxtools/settings.py
kmaxtools/vcommon.py
kmaxtools.egg-info/PKG-INFO
kmaxtools.egg-info/SOURCES.txt
kmaxtools.egg-info/dependency_links.txt
kmaxtools.egg-info/requires.txt
kmaxtools.egg-info/top_level.txt
pymake/__init__.py
pymake/builtins.py
pymake/command.py
pymake/data.py
pymake/functions.py
pymake/globrelative.py
pymake/implicit.py
pymake/parser.py
pymake/parserdata.py
pymake/process.py
pymake/util.py
pymake/win32process.py